{
  "engine": "openairedatasets",
  "case": "live",
  "query": {
    "query": "rust",
    "pageno": 1,
    "safesearch": "Off",
    "time_range": null,
    "locale": "all",
    "categories": [],
    "engines": []
  },
  "golden_request": {
    "query": "rust",
    "category": "",
    "pageno": 1,
    "safesearch": "Off",
    "time_range": null,
    "locale_key": "all",
    "engine_data": {},
    "method": "Get",
    "url": "https://api.openaire.eu/search/datasets?format=json&page=1&size=10&title=rust",
    "headers": {},
    "cookies": {},
    "data": {},
    "json": null,
    "content": "",
    "allow_redirects": false,
    "max_redirects": 0,
    "soft_max_redirects": 0,
    "auth": null,
    "verify": "Default",
    "raise_for_httperror": false,
    "network": null
  },
  "response": {
    "status": 200,
    "url": "https://api.openaire.eu/search/datasets?format=json&page=1&size=10&title=rust",
    "headers": {
      "content-type": "application/json;charset=UTF-8",
      "x-ratelimit-used": "13",
      "x-ratelimit-limit": "7199",
      "transfer-encoding": "chunked",
      "date": "Thu, 09 Jul 2026 14:06:04 GMT"
    },
    "body": "{ \"response\" : { \"header\" : { \"query\" : { \"$\" : \"(oaftype exact result) and (resulttypeid exact dataset) and (resulttitle exact \\\"rust\\\")\" }, \"locale\" : { \"$\" : \"en_US\" }, \"size\" : { \"$\" : 10 }, \"page\" : { \"$\" : 1 }, \"total\" : { \"$\" : 2176 }, \"fields\" : null }, \"results\" : { \"result\" : [ { \"header\" : { \"dri:objIdentifier\" : { \"$\" : \"doi_________::09fefb2afe1b7526caac912775500898\" }, \"dri:dateOfCollection\" : { \"$\" : \"2026-06-23T10:03:50.798626879\" }, \"dri:dateOfTransformation\" : { \"$\" : \"2022-09-12T14:35:33+0000\" } }, \"metadata\" : { \"oaf:entity\" : { \"@xsi:schemaLocation\" : \"http://namespace.openaire.eu/oaf https://www.openaire.eu/schema/1.0/oaf-1.0.xsd\", \"oaf:result\" : { \"collectedfrom\" : { \"@name\" : \"Datacite\", \"@id\" : \"openaire____::9e3be59865b2c1c335d32dae2fe7b254\" }, \"originalId\" : [ { \"$\" : \"50|datacite____::09fefb2afe1b7526caac912775500898\" }, { \"$\" : \"10.5446/s_1065\" } ], \"pid\" : { \"@classid\" : \"doi\", \"@classname\" : \"Digital Object Identifier\", \"@schemeid\" : \"dnet:pid_types\", \"@schemename\" : \"dnet:pid_types\", \"@inferred\" : false, \"@provenanceaction\" : \"sysimport:actionset\", \"@trust\" : \"0.9\", \"$\" : \"10.5446/s_1065\" }, \"measure\" : [ { \"@id\" : \"influence\", \"@score\" : \"2.2251732E-9\", \"@class\" : \"C5\" }, { \"@id\" : \"popularity\", \"@score\" : \"6.971976E-10\", \"@class\" : \"C5\" }, { \"@id\" : \"influence_alt\", \"@score\" : \"0\", \"@class\" : \"C5\" }, { \"@id\" : \"citationCount\", \"@score\" : \"0\", \"@class\" : \"C5\" }, { \"@id\" : \"popularity_alt\", \"@score\" : \"0.0\", \"@class\" : \"C5\" }, { \"@id\" : \"impulse\", \"@score\" : \"0\", \"@class\" : \"C5\" } ], \"title\" : { \"@classid\" : \"main title\", \"@classname\" : \"main title\", \"@schemeid\" : \"dnet:dataCite_title\", \"@schemename\" : \"dnet:dataCite_title\", \"$\" : \"Rust Belt Rust 2016\" }, \"bestaccessright\" : { \"@classid\" : \"UNKNOWN\", \"@classname\" : \"unspecified\", \"@schemeid\" : \"dnet:access_modes\", \"@schemename\" : \"dnet:access_modes\" }, \"creator\" : { \"@rank\" : \"1\", \"$\" : \"Rust Belt Rust Conference\" }, \"dateofacceptance\" : { \"$\" : \"2016-01-01\" }, \"subject\" : { \"@classid\" : \"keyword\", \"@classname\" : \"keyword\", \"@schemeid\" : \"dnet:subject_classification_typologies\", \"@schemename\" : \"dnet:subject_classification_typologies\", \"$\" : \"Information Technology\" }, \"language\" : { \"@classid\" : \"und\", \"@classname\" : \"Undetermined\", \"@schemeid\" : \"dnet:languages\", \"@schemename\" : \"dnet:languages\" }, \"relevantdate\" : { \"@classid\" : \"issued\", \"@classname\" : \"issued\", \"@schemeid\" : \"dnet:dataCite_date\", \"@schemename\" : \"dnet:dataCite_date\", \"$\" : \"2016-01-01\" }, \"resulttype\" : { \"@classid\" : \"dataset\", \"@classname\" : \"dataset\", \"@schemeid\" : \"dnet:result_typologies\", \"@schemename\" : \"dnet:result_typologies\" }, \"resourcetype\" : { \"@classid\" : \"UNKNOWN\", \"@classname\" : \"UNKNOWN\", \"@schemeid\" : \"dnet:dataCite_resource\", \"@schemename\" : \"dnet:dataCite_resource\" }, \"datainfo\" : { \"inferred\" : { \"$\" : false }, \"deletedbyinference\" : { \"$\" : false }, \"trust\" : { \"$\" : \"0.9\" }, \"inferenceprovenance\" : { \"$\" : \"null\" }, \"provenanceaction\" : { \"@classid\" : \"sysimport:actionset\", \"@classname\" : \"Harvested\", \"@schemeid\" : \"dnet:provenanceActions\", \"@schemename\" : \"dnet:provenanceActions\" } }, \"rels\" : null, \"children\" : { \"instance\" : { \"accessright\" : { \"@classid\" : \"UNKNOWN\", \"@classname\" : \"unspecified\", \"@schemeid\" : \"dnet:access_modes\", \"@schemename\" : \"dnet:access_modes\" }, \"collectedfrom\" : { \"@name\" : \"Datacite\", \"@id\" : \"openaire____::9e3be59865b2c1c335d32dae2fe7b254\" }, \"hostedby\" : { \"@name\" : \"Unknown Repository\", \"@id\" : \"openaire____::55045bd2a65019fd8e6741a755395c8c\" }, \"dateofacceptance\" : { \"$\" : \"2016-01-01\" }, \"instancetype\" : { \"@classid\" : \"0022\", \"@classname\" : \"Collection\", \"@schemeid\" : \"dnet:publication_resource\", \"@schemename\" : \"dnet:publication_resource\" }, \"pid\" : { \"@classid\" : \"doi\", \"@classname\" : \"Digital Object Identifier\", \"@schemeid\" : \"dnet:pid_types\", \"@schemename\" : \"dnet:pid_types\", \"@inferred\" : false, \"@provenanceaction\" : \"sysimport:actionset\", \"@trust\" : \"0.9\", \"$\" : \"10.5446/s_1065\" }, \"refereed\" : { \"@classid\" : \"0002\", \"@classname\" : \"nonPeerReviewed\", \"@schemeid\" : \"dnet:review_levels\", \"@schemename\" : \"dnet:review_levels\" }, \"webresource\" : { \"url\" : { \"$\" : \"https://doi.org/10.5446/s_1065\" } } } } } } } }, { \"header\" : { \"dri:objIdentifier\" : { \"$\" : \"doi_________::c8e2b11f2f6042c1cda57661c249d8b7\" }, \"dri:dateOfCollection\" : { \"$\" : \"2026-06-23T10:03:00.946272627\" }, \"dri:dateOfTransformation\" : null }, \"metadata\" : { \"oaf:entity\" : { \"@xsi:schemaLocation\" : \"http://namespace.openaire.eu/oaf https://www.openaire.eu/schema/1.0/oaf-1.0.xsd\", \"oaf:result\" : { \"collectedfrom\" : { \"@name\" : \"Crossref\", \"@id\" : \"openaire____::081b82f96300b6a6e3d282bad31cb6e2\" }, \"originalId\" : [ { \"$\" : \"10.24894/sprengglossarium_r05031\" }, { \"$\" : \"50|doiboost____|c8e2b11f2f6042c1cda57661c249d8b7\" } ], \"pid\" : { \"@classid\" : \"doi\", \"@classname\" : \"Digital Object Identifier\", \"@schemeid\" : \"dnet:pid_types\", \"@schemename\" : \"dnet:pid_types\", \"$\" : \"10.24894/sprengglossarium_r05031\" }, \"measure\" : [ { \"@id\" : \"influence\", \"@score\" : \"2.2251732E-9\", \"@class\" : \"C5\" }, { \"@id\" : \"popularity\", \"@score\" : \"2.342466E-9\", \"@class\" : \"C5\" }, { \"@id\" : \"influence_alt\", \"@score\" : \"0\", \"@class\" : \"C5\" }, { \"@id\" : \"citationCount\", \"@score\" : \"0\", \"@class\" : \"C5\" }, { \"@id\" : \"popularity_alt\", \"@score\" : \"0.0\", \"@class\" : \"C5\" }, { \"@id\" : \"impulse\", \"@score\" : \"0\", \"@class\" : \"C5\" } ], \"title\" : { \"@classid\" : \"main title\", \"@classname\" : \"main title\", \"@schemeid\" : \"dnet:dataCite_title\", \"@schemename\" : \"dnet:dataCite_title\", \"$\" : \"rust\" }, \"bestaccessright\" : { \"@classid\" : \"UNKNOWN\", \"@classname\" : \"unspecified\", \"@schemeid\" : \"dnet:access_modes\", \"@schemename\" : \"dnet:access_modes\" }, \"dateofacceptance\" : { \"$\" : \"2025-01-01\" }, \"language\" : { \"@classid\" : \"und\", \"@classname\" : \"Undetermined\", \"@schemeid\" : \"dnet:languages\", \"@schemename\" : \"dnet:languages\" }, \"relevantdate\" : [ { \"@classid\" : \"created\", \"@classname\" : \"created\", \"@schemeid\" : \"dnet:dataCite_date\", \"@schemename\" : \"dnet:dataCite_date\", \"$\" : \"2025-02-13\" }, { \"@classid\" : \"published-print\", \"@classname\" : \"published-print\", \"@schemeid\" : \"dnet:dataCite_date\", \"@schemename\" : \"dnet:dataCite_date\", \"$\" : \"2025-01-01\" } ], \"publisher\" : { \"$\" : \"Schwabe Verlag\" }, \"source\" : { \"$\" : \"Crossref\" }, \"resulttype\" : { \"@classid\" : \"dataset\", \"@classname\" : \"dataset\", \"@schemeid\" : \"dnet:result_typologies\", \"@schemename\" : \"dnet:result_typologies\" }, \"resourcetype\" : { \"@classid\" : \"dataset\", \"@classname\" : \"dataset\", \"@schemeid\" : \"dnet:result_typologies\", \"@schemename\" : \"dnet:result_typologies\" }, \"datainfo\" : { \"inferred\" : { \"$\" : false }, \"deletedbyinference\" : { \"$\" : false }, \"trust\" : { \"$\" : \"0.91\" }, \"inferenceprovenance\" : { \"$\" : \"null\" }, \"provenanceaction\" : { \"@classid\" : \"sysimport:actionset\", \"@classname\" : \"Harvested\", \"@schemeid\" : \"dnet:provenanceActions\", \"@schemename\" : \"dnet:provenanceActions\" } }, \"rels\" : null, \"children\" : { \"instance\" : { \"accessright\" : { \"@classid\" : \"UNKNOWN\", \"@classname\" : \"unspecified\", \"@schemeid\" : \"dnet:access_modes\", \"@schemename\" : \"dnet:access_modes\" }, \"collectedfrom\" : { \"@name\" : \"Crossref\", \"@id\" : \"openaire____::081b82f96300b6a6e3d282bad31cb6e2\" }, \"hostedby\" : { \"@name\" : \"Unknown Repository\", \"@id\" : \"openaire____::55045bd2a65019fd8e6741a755395c8c\" }, \"dateofacceptance\" : { \"$\" : \"2025-01-01\" }, \"instancetype\" : { \"@classid\" : \"0021\", \"@classname\" : \"Dataset\", \"@schemeid\" : \"dnet:publication_resource\", \"@schemename\" : \"dnet:publication_resource\" }, \"pid\" : { \"@classid\" : \"doi\", \"@classname\" : \"Digital Object Identifier\", \"@schemeid\" : \"dnet:pid_types\", \"@schemename\" : \"dnet:pid_types\", \"$\" : \"10.24894/sprengglossarium_r05031\" }, \"refereed\" : { \"@classid\" : \"0002\", \"@classname\" : \"nonPeerReviewed\", \"@schemeid\" : \"dnet:review_levels\", \"@schemename\" : \"dnet:review_levels\" }, \"webresource\" : { \"url\" : { \"$\" : \"https://doi.org/10.24894/sprengglossarium_r05031\" } } } } } } } }, { \"header\" : { \"dri:objIdentifier\" : { \"$\" : \"doi_________::87285495490680a4adf5adc6286f8d16\" }, \"dri:dateOfCollection\" : { \"$\" : \"2026-06-23T10:03:02.619515278\" }, \"dri:dateOfTransformation\" : { \"$\" : \"2022-10-12T15:52:29+0000\" } }, \"metadata\" : { \"oaf:entity\" : { \"@xsi:schemaLocation\" : \"http://namespace.openaire.eu/oaf https://www.openaire.eu/schema/1.0/oaf-1.0.xsd\", \"oaf:result\" : { \"collectedfrom\" : { \"@name\" : \"Datacite\", \"@id\" : \"openaire____::9e3be59865b2c1c335d32dae2fe7b254\" }, \"originalId\" : [ { \"$\" : \"50|datacite____::87285495490680a4adf5adc6286f8d16\" }, { \"$\" : \"10.5446/s_1055\" } ], \"pid\" : { \"@classid\" : \"doi\", \"@classname\" : \"Digital Object Identifier\", \"@schemeid\" : \"dnet:pid_types\", \"@schemename\" : \"dnet:pid_types\", \"@inferred\" : false, \"@provenanceaction\" : \"sysimport:actionset\", \"@trust\" : \"0.9\", \"$\" : \"10.5446/s_1055\" }, \"measure\" : [ { \"@id\" : \"influence\", \"@score\" : \"2.2251732E-9\", \"@class\" : \"C5\" }, { \"@id\" : \"popularity\", \"@score\" : \"1.0119146E-9\", \"@class\" : \"C5\" }, { \"@id\" : \"influence_alt\", \"@score\" : \"0\", \"@class\" : \"C5\" }, { \"@id\" : \"citationCount\", \"@score\" : \"0\", \"@class\" : \"C5\" }, { \"@id\" : \"popularity_alt\", \"@score\" : \"0.0\", \"@class\" : \"C5\" }, { \"@id\" : \"impulse\", \"@score\" : \"0\", \"@class\" : \"C5\" } ], \"title\" : { \"@classid\" : \"main title\", \"@classname\" : \"main title\", \"@schemeid\" : \"dnet:dataCite_title\", \"@schemename\" : \"dnet:dataCite_title\", \"$\" : \"Rust Belt Rust Conference 2019\" }, \"bestaccessright\" : { \"@classid\" : \"UNKNOWN\", \"@classname\" : \"unspecified\", \"@schemeid\" : \"dnet:access_modes\", \"@schemename\" : \"dnet:access_modes\" }, \"creator\" : { \"@rank\" : \"1\", \"$\" : \"Rust Belt Rust Conference\" }, \"dateofacceptance\" : { \"$\" : \"2019-01-01\" }, \"subject\" : { \"@classid\" : \"keyword\", \"@classname\" : \"keyword\", \"@schemeid\" : \"dnet:subject_classification_typologies\", \"@schemename\" : \"dnet:subject_classification_typologies\", \"$\" : \"Information Technology\" }, \"language\" : { \"@classid\" : \"und\", \"@classname\" : \"Undetermined\", \"@schemeid\" : \"dnet:languages\", \"@schemename\" : \"dnet:languages\" }, \"relevantdate\" : { \"@classid\" : \"issued\", \"@classname\" : \"issued\", \"@schemeid\" : \"dnet:dataCite_date\", \"@schemename\" : \"dnet:dataCite_date\", \"$\" : \"2019-01-01\" }, \"resulttype\" : { \"@classid\" : \"dataset\", \"@classname\" : \"dataset\", \"@schemeid\" : \"dnet:result_typologies\", \"@schemename\" : \"dnet:result_typologies\" }, \"resourcetype\" : { \"@classid\" : \"UNKNOWN\", \"@classname\" : \"UNKNOWN\", \"@schemeid\" : \"dnet:dataCite_resource\", \"@schemename\" : \"dnet:dataCite_resource\" }, \"datainfo\" : { \"inferred\" : { \"$\" : false }, \"deletedbyinference\" : { \"$\" : false }, \"trust\" : { \"$\" : \"0.9\" }, \"inferenceprovenance\" : { \"$\" : \"null\" }, \"provenanceaction\" : { \"@classid\" : \"sysimport:actionset\", \"@classname\" : \"Harvested\", \"@schemeid\" : \"dnet:provenanceActions\", \"@schemename\" : \"dnet:provenanceActions\" } }, \"rels\" : null, \"children\" : { \"instance\" : { \"accessright\" : { \"@classid\" : \"UNKNOWN\", \"@classname\" : \"unspecified\", \"@schemeid\" : \"dnet:access_modes\", \"@schemename\" : \"dnet:access_modes\" }, \"collectedfrom\" : { \"@name\" : \"Datacite\", \"@id\" : \"openaire____::9e3be59865b2c1c335d32dae2fe7b254\" }, \"hostedby\" : { \"@name\" : \"Unknown Repository\", \"@id\" : \"openaire____::55045bd2a65019fd8e6741a755395c8c\" }, \"dateofacceptance\" : { \"$\" : \"2019-01-01\" }, \"instancetype\" : { \"@classid\" : \"0022\", \"@classname\" : \"Collection\", \"@schemeid\" : \"dnet:publication_resource\", \"@schemename\" : \"dnet:publication_resource\" }, \"pid\" : { \"@classid\" : \"doi\", \"@classname\" : \"Digital Object Identifier\", \"@schemeid\" : \"dnet:pid_types\", \"@schemename\" : \"dnet:pid_types\", \"@inferred\" : false, \"@provenanceaction\" : \"sysimport:actionset\", \"@trust\" : \"0.9\", \"$\" : \"10.5446/s_1055\" }, \"refereed\" : { \"@classid\" : \"0002\", \"@classname\" : \"nonPeerReviewed\", \"@schemeid\" : \"dnet:review_levels\", \"@schemename\" : \"dnet:review_levels\" }, \"webresource\" : { \"url\" : { \"$\" : \"https://doi.org/10.5446/s_1055\" } } } } } } } }, { \"header\" : { \"dri:objIdentifier\" : { \"$\" : \"doi_________::15f3227ab9702441b2c617c101c56692\" }, \"dri:dateOfCollection\" : { \"$\" : \"2026-06-23T10:03:16.876683311\" }, \"dri:dateOfTransformation\" : null }, \"metadata\" : { \"oaf:entity\" : { \"@xsi:schemaLocation\" : \"http://namespace.openaire.eu/oaf https://www.openaire.eu/schema/1.0/oaf-1.0.xsd\", \"oaf:result\" : { \"collectedfrom\" : { \"@name\" : \"Crossref\", \"@id\" : \"openaire____::081b82f96300b6a6e3d282bad31cb6e2\" }, \"originalId\" : [ { \"$\" : \"10.24894/sprengglossarium_r05025\" }, { \"$\" : \"50|doiboost____|15f3227ab9702441b2c617c101c56692\" } ], \"pid\" : { \"@classid\" : \"doi\", \"@classname\" : \"Digital Object Identifier\", \"@schemeid\" : \"dnet:pid_types\", \"@schemename\" : \"dnet:pid_types\", \"$\" : \"10.24894/sprengglossarium_r05025\" }, \"measure\" : [ { \"@id\" : \"influence\", \"@score\" : \"2.2251732E-9\", \"@class\" : \"C5\" }, { \"@id\" : \"popularity\", \"@score\" : \"2.342466E-9\", \"@class\" : \"C5\" }, { \"@id\" : \"influence_alt\", \"@score\" : \"0\", \"@class\" : \"C5\" }, { \"@id\" : \"citationCount\", \"@score\" : \"0\", \"@class\" : \"C5\" }, { \"@id\" : \"popularity_alt\", \"@score\" : \"0.0\", \"@class\" : \"C5\" }, { \"@id\" : \"impulse\", \"@score\" : \"0\", \"@class\" : \"C5\" } ], \"title\" : { \"@classid\" : \"main title\", \"@classname\" : \"main title\", \"@schemeid\" : \"dnet:dataCite_title\", \"@schemename\" : \"dnet:dataCite_title\", \"$\" : \"Rust\" }, \"bestaccessright\" : { \"@classid\" : \"UNKNOWN\", \"@classname\" : \"unspecified\", \"@schemeid\" : \"dnet:access_modes\", \"@schemename\" : \"dnet:access_modes\" }, \"dateofacceptance\" : { \"$\" : \"2025-01-01\" }, \"language\" : { \"@classid\" : \"und\", \"@classname\" : \"Undetermined\", \"@schemeid\" : \"dnet:languages\", \"@schemename\" : \"dnet:languages\" }, \"relevantdate\" : [ { \"@classid\" : \"created\", \"@classname\" : \"created\", \"@schemeid\" : \"dnet:dataCite_date\", \"@schemename\" : \"dnet:dataCite_date\", \"$\" : \"2025-02-13\" }, { \"@classid\" : \"published-print\", \"@classname\" : \"published-print\", \"@schemeid\" : \"dnet:dataCite_date\", \"@schemename\" : \"dnet:dataCite_date\", \"$\" : \"2025-01-01\" } ], \"publisher\" : { \"$\" : \"Schwabe Verlag\" }, \"source\" : { \"$\" : \"Crossref\" }, \"resulttype\" : { \"@classid\" : \"dataset\", \"@classname\" : \"dataset\", \"@schemeid\" : \"dnet:result_typologies\", \"@schemename\" : \"dnet:result_typologies\" }, \"resourcetype\" : { \"@classid\" : \"dataset\", \"@classname\" : \"dataset\", \"@schemeid\" : \"dnet:result_typologies\", \"@schemename\" : \"dnet:result_typologies\" }, \"datainfo\" : { \"inferred\" : { \"$\" : false }, \"deletedbyinference\" : { \"$\" : false }, \"trust\" : { \"$\" : \"0.91\" }, \"inferenceprovenance\" : { \"$\" : \"null\" }, \"provenanceaction\" : { \"@classid\" : \"sysimport:actionset\", \"@classname\" : \"Harvested\", \"@schemeid\" : \"dnet:provenanceActions\", \"@schemename\" : \"dnet:provenanceActions\" } }, \"rels\" : null, \"children\" : { \"instance\" : { \"accessright\" : { \"@classid\" : \"UNKNOWN\", \"@classname\" : \"unspecified\", \"@schemeid\" : \"dnet:access_modes\", \"@schemename\" : \"dnet:access_modes\" }, \"collectedfrom\" : { \"@name\" : \"Crossref\", \"@id\" : \"openaire____::081b82f96300b6a6e3d282bad31cb6e2\" }, \"hostedby\" : { \"@name\" : \"Unknown Repository\", \"@id\" : \"openaire____::55045bd2a65019fd8e6741a755395c8c\" }, \"dateofacceptance\" : { \"$\" : \"2025-01-01\" }, \"instancetype\" : { \"@classid\" : \"0021\", \"@classname\" : \"Dataset\", \"@schemeid\" : \"dnet:publication_resource\", \"@schemename\" : \"dnet:publication_resource\" }, \"pid\" : { \"@classid\" : \"doi\", \"@classname\" : \"Digital Object Identifier\", \"@schemeid\" : \"dnet:pid_types\", \"@schemename\" : \"dnet:pid_types\", \"$\" : \"10.24894/sprengglossarium_r05025\" }, \"refereed\" : { \"@classid\" : \"0002\", \"@classname\" : \"nonPeerReviewed\", \"@schemeid\" : \"dnet:review_levels\", \"@schemename\" : \"dnet:review_levels\" }, \"webresource\" : { \"url\" : { \"$\" : \"https://doi.org/10.24894/sprengglossarium_r05025\" } } } } } } } }, { \"header\" : { \"dri:objIdentifier\" : { \"$\" : \"doi_________::782b2f1609ed7bb729e6d2d0683b4a41\" }, \"dri:dateOfCollection\" : { \"$\" : \"2026-06-23T10:03:14.216126342\" }, \"dri:dateOfTransformation\" : null }, \"metadata\" : { \"oaf:entity\" : { \"@xsi:schemaLocation\" : \"http://namespace.openaire.eu/oaf https://www.openaire.eu/schema/1.0/oaf-1.0.xsd\", \"oaf:result\" : { \"collectedfrom\" : { \"@name\" : \"Crossref\", \"@id\" : \"openaire____::081b82f96300b6a6e3d282bad31cb6e2\" }, \"originalId\" : [ { \"$\" : \"10.24894/sprengglossarium_r05023\" }, { \"$\" : \"50|doiboost____|782b2f1609ed7bb729e6d2d0683b4a41\" } ], \"pid\" : { \"@classid\" : \"doi\", \"@classname\" : \"Digital Object Identifier\", \"@schemeid\" : \"dnet:pid_types\", \"@schemename\" : \"dnet:pid_types\", \"$\" : \"10.24894/sprengglossarium_r05023\" }, \"measure\" : [ { \"@id\" : \"influence\", \"@score\" : \"2.2251732E-9\", \"@class\" : \"C5\" }, { \"@id\" : \"popularity\", \"@score\" : \"2.342466E-9\", \"@class\" : \"C5\" }, { \"@id\" : \"influence_alt\", \"@score\" : \"0\", \"@class\" : \"C5\" }, { \"@id\" : \"citationCount\", \"@score\" : \"0\", \"@class\" : \"C5\" }, { \"@id\" : \"popularity_alt\", \"@score\" : \"0.0\", \"@class\" : \"C5\" }, { \"@id\" : \"impulse\", \"@score\" : \"0\", \"@class\" : \"C5\" } ], \"title\" : { \"@classid\" : \"main title\", \"@classname\" : \"main title\", \"@schemeid\" : \"dnet:dataCite_title\", \"@schemename\" : \"dnet:dataCite_title\", \"$\" : \"rust\" }, \"bestaccessright\" : { \"@classid\" : \"UNKNOWN\", \"@classname\" : \"unspecified\", \"@schemeid\" : \"dnet:access_modes\", \"@schemename\" : \"dnet:access_modes\" }, \"dateofacceptance\" : { \"$\" : \"2025-01-01\" }, \"language\" : { \"@classid\" : \"und\", \"@classname\" : \"Undetermined\", \"@schemeid\" : \"dnet:languages\", \"@schemename\" : \"dnet:languages\" }, \"relevantdate\" : [ { \"@classid\" : \"created\", \"@classname\" : \"created\", \"@schemeid\" : \"dnet:dataCite_date\", \"@schemename\" : \"dnet:dataCite_date\", \"$\" : \"2025-02-13\" }, { \"@classid\" : \"published-print\", \"@classname\" : \"published-print\", \"@schemeid\" : \"dnet:dataCite_date\", \"@schemename\" : \"dnet:dataCite_date\", \"$\" : \"2025-01-01\" } ], \"publisher\" : { \"$\" : \"Schwabe Verlag\" }, \"source\" : { \"$\" : \"Crossref\" }, \"resulttype\" : { \"@classid\" : \"dataset\", \"@classname\" : \"dataset\", \"@schemeid\" : \"dnet:result_typologies\", \"@schemename\" : \"dnet:result_typologies\" }, \"resourcetype\" : { \"@classid\" : \"dataset\", \"@classname\" : \"dataset\", \"@schemeid\" : \"dnet:result_typologies\", \"@schemename\" : \"dnet:result_typologies\" }, \"datainfo\" : { \"inferred\" : { \"$\" : false }, \"deletedbyinference\" : { \"$\" : false }, \"trust\" : { \"$\" : \"0.91\" }, \"inferenceprovenance\" : { \"$\" : \"null\" }, \"provenanceaction\" : { \"@classid\" : \"sysimport:actionset\", \"@classname\" : \"Harvested\", \"@schemeid\" : \"dnet:provenanceActions\", \"@schemename\" : \"dnet:provenanceActions\" } }, \"rels\" : null, \"children\" : { \"instance\" : { \"accessright\" : { \"@classid\" : \"UNKNOWN\", \"@classname\" : \"unspecified\", \"@schemeid\" : \"dnet:access_modes\", \"@schemename\" : \"dnet:access_modes\" }, \"collectedfrom\" : { \"@name\" : \"Crossref\", \"@id\" : \"openaire____::081b82f96300b6a6e3d282bad31cb6e2\" }, \"hostedby\" : { \"@name\" : \"Unknown Repository\", \"@id\" : \"openaire____::55045bd2a65019fd8e6741a755395c8c\" }, \"dateofacceptance\" : { \"$\" : \"2025-01-01\" }, \"instancetype\" : { \"@classid\" : \"0021\", \"@classname\" : \"Dataset\", \"@schemeid\" : \"dnet:publication_resource\", \"@schemename\" : \"dnet:publication_resource\" }, \"pid\" : { \"@classid\" : \"doi\", \"@classname\" : \"Digital Object Identifier\", \"@schemeid\" : \"dnet:pid_types\", \"@schemename\" : \"dnet:pid_types\", \"$\" : \"10.24894/sprengglossarium_r05023\" }, \"refereed\" : { \"@classid\" : \"0002\", \"@classname\" : \"nonPeerReviewed\", \"@schemeid\" : \"dnet:review_levels\", \"@schemename\" : \"dnet:review_levels\" }, \"webresource\" : { \"url\" : { \"$\" : \"https://doi.org/10.24894/sprengglossarium_r05023\" } } } } } } } }, { \"header\" : { \"dri:objIdentifier\" : { \"$\" : \"doi_________::4bcca1ecfe76500cde944ad34c075db7\" }, \"dri:dateOfCollection\" : { \"$\" : \"2026-06-23T10:03:07.676678759\" }, \"dri:dateOfTransformation\" : null }, \"metadata\" : { \"oaf:entity\" : { \"@xsi:schemaLocation\" : \"http://namespace.openaire.eu/oaf https://www.openaire.eu/schema/1.0/oaf-1.0.xsd\", \"oaf:result\" : { \"collectedfrom\" : { \"@name\" : \"Crossref\", \"@id\" : \"openaire____::081b82f96300b6a6e3d282bad31cb6e2\" }, \"originalId\" : [ { \"$\" : \"10.1163/2405-8262_rgg4_sim_025121\" }, { \"$\" : \"50|doiboost____|4bcca1ecfe76500cde944ad34c075db7\" } ], \"pid\" : { \"@classid\" : \"doi\", \"@classname\" : \"Digital Object Identifier\", \"@schemeid\" : \"dnet:pid_types\", \"@schemename\" : \"dnet:pid_types\", \"$\" : \"10.1163/2405-8262_rgg4_sim_025121\" }, \"measure\" : [ { \"@id\" : \"influence\", \"@score\" : \"2.2251732E-9\", \"@class\" : \"C5\" }, { \"@id\" : \"popularity\", \"@score\" : \"6.2166633E-10\", \"@class\" : \"C5\" }, { \"@id\" : \"influence_alt\", \"@score\" : \"0\", \"@class\" : \"C5\" }, { \"@id\" : \"citationCount\", \"@score\" : \"0\", \"@class\" : \"C5\" }, { \"@id\" : \"popularity_alt\", \"@score\" : \"0.0\", \"@class\" : \"C5\" }, { \"@id\" : \"impulse\", \"@score\" : \"0\", \"@class\" : \"C5\" } ], \"title\" : { \"@classid\" : \"main title\", \"@classname\" : \"main title\", \"@schemeid\" : \"dnet:dataCite_title\", \"@schemename\" : \"dnet:dataCite_title\", \"$\" : \"Rust\" }, \"bestaccessright\" : { \"@classid\" : \"UNKNOWN\", \"@classname\" : \"unspecified\", \"@schemeid\" : \"dnet:access_modes\", \"@schemename\" : \"dnet:access_modes\" }, \"dateofacceptance\" : { \"$\" : \"2015-07-20\" }, \"language\" : { \"@classid\" : \"und\", \"@classname\" : \"Undetermined\", \"@schemeid\" : \"dnet:languages\", \"@schemename\" : \"dnet:languages\" }, \"relevantdate\" : { \"@classid\" : \"created\", \"@classname\" : \"created\", \"@schemeid\" : \"dnet:dataCite_date\", \"@schemename\" : \"dnet:dataCite_date\", \"$\" : \"2015-07-20\" }, \"publisher\" : { \"$\" : \"Walter de Gruyter GmbH\" }, \"source\" : { \"$\" : \"Crossref\" }, \"resulttype\" : { \"@classid\" : \"dataset\", \"@classname\" : \"dataset\", \"@schemeid\" : \"dnet:result_typologies\", \"@schemename\" : \"dnet:result_typologies\" }, \"resourcetype\" : { \"@classid\" : \"dataset\", \"@classname\" : \"dataset\", \"@schemeid\" : \"dnet:result_typologies\", \"@schemename\" : \"dnet:result_typologies\" }, \"datainfo\" : { \"inferred\" : { \"$\" : false }, \"deletedbyinference\" : { \"$\" : false }, \"trust\" : { \"$\" : \"0.91\" }, \"inferenceprovenance\" : { \"$\" : \"null\" }, \"provenanceaction\" : { \"@classid\" : \"sysimport:actionset\", \"@classname\" : \"Harvested\", \"@schemeid\" : \"dnet:provenanceActions\", \"@schemename\" : \"dnet:provenanceActions\" } }, \"rels\" : null, \"children\" : { \"instance\" : { \"accessright\" : { \"@classid\" : \"UNKNOWN\", \"@classname\" : \"unspecified\", \"@schemeid\" : \"dnet:access_modes\", \"@schemename\" : \"dnet:access_modes\" }, \"collectedfrom\" : { \"@name\" : \"Crossref\", \"@id\" : \"openaire____::081b82f96300b6a6e3d282bad31cb6e2\" }, \"hostedby\" : { \"@name\" : \"Unknown Repository\", \"@id\" : \"openaire____::55045bd2a65019fd8e6741a755395c8c\" }, \"dateofacceptance\" : { \"$\" : \"2015-07-20\" }, \"instancetype\" : { \"@classid\" : \"0021\", \"@classname\" : \"Dataset\", \"@schemeid\" : \"dnet:publication_resource\", \"@schemename\" : \"dnet:publication_resource\" }, \"pid\" : { \"@classid\" : \"doi\", \"@classname\" : \"Digital Object Identifier\", \"@schemeid\" : \"dnet:pid_types\", \"@schemename\" : \"dnet:pid_types\", \"$\" : \"10.1163/2405-8262_rgg4_sim_025121\" }, \"refereed\" : { \"@classid\" : \"0002\", \"@classname\" : \"nonPeerReviewed\", \"@schemeid\" : \"dnet:review_levels\", \"@schemename\" : \"dnet:review_levels\" }, \"webresource\" : { \"url\" : { \"$\" : \"https://doi.org/10.1163/2405-8262_rgg4_sim_025121\" } } } } } } } }, { \"header\" : { \"dri:objIdentifier\" : { \"$\" : \"doi_________::42c3466bc134df4896475273e10eb43b\" }, \"dri:dateOfCollection\" : { \"$\" : \"2026-06-23T10:03:50.070920317\" }, \"dri:dateOfTransformation\" : null }, \"metadata\" : { \"oaf:entity\" : { \"@xsi:schemaLocation\" : \"http://namespace.openaire.eu/oaf https://www.openaire.eu/schema/1.0/oaf-1.0.xsd\", \"oaf:result\" : { \"collectedfrom\" : { \"@name\" : \"Crossref\", \"@id\" : \"openaire____::081b82f96300b6a6e3d282bad31cb6e2\" }, \"originalId\" : [ { \"$\" : \"10.1079/pwkb.20167801211\" }, { \"$\" : \"50|doiboost____|42c3466bc134df4896475273e10eb43b\" } ], \"pid\" : { \"@classid\" : \"doi\", \"@classname\" : \"Digital Object Identifier\", \"@schemeid\" : \"dnet:pid_types\", \"@schemename\" : \"dnet:pid_types\", \"$\" : \"10.1079/pwkb.20167801211\" }, \"measure\" : [ { \"@id\" : \"influence\", \"@score\" : \"2.2251732E-9\", \"@class\" : \"C5\" }, { \"@id\" : \"popularity\", \"@score\" : \"1.1551581E-9\", \"@class\" : \"C5\" }, { \"@id\" : \"influence_alt\", \"@score\" : \"0\", \"@class\" : \"C5\" }, { \"@id\" : \"citationCount\", \"@score\" : \"0\", \"@class\" : \"C5\" }, { \"@id\" : \"popularity_alt\", \"@score\" : \"0.0\", \"@class\" : \"C5\" }, { \"@id\" : \"impulse\", \"@score\" : \"0\", \"@class\" : \"C5\" } ], \"title\" : [ { \"@classid\" : \"main title\", \"@classname\" : \"main title\", \"@schemeid\" : \"dnet:dataCite_title\", \"@schemename\" : \"dnet:dataCite_title\", \"$\" : \"Stem rust (black rust) on wheat-Ethiopia\" }, { \"@classid\" : \"subtitle\", \"@classname\" : \"subtitle\", \"@schemeid\" : \"dnet:dataCite_title\", \"@schemename\" : \"dnet:dataCite_title\", \"$\" : \"<i>Puccinia graminis</i>             ; Agada wagi or wagi jirma\" } ], \"bestaccessright\" : { \"@classid\" : \"UNKNOWN\", \"@classname\" : \"unspecified\", \"@schemeid\" : \"dnet:access_modes\", \"@schemename\" : \"dnet:access_modes\" }, \"creator\" : { \"@rank\" : \"1\", \"@name\" : \"H.\", \"@surname\" : \"Kassa\", \"$\" : \"H. Kassa\" }, \"dateofacceptance\" : { \"$\" : \"2020-02-01\" }, \"subject\" : [ { \"@classid\" : \"FOS\", \"@classname\" : \"Fields of Science and Technology classification\", \"@schemeid\" : \"dnet:subject_classification_typologies\", \"@schemename\" : \"dnet:subject_classification_typologies\", \"@inferred\" : true, \"@inferenceprovenance\" : \"update\", \"@provenanceaction\" : \"subject:fos\", \"$\" : \"0301 basic medicine\" }, { \"@classid\" : \"FOS\", \"@classname\" : \"Fields of Science and Technology classification\", \"@schemeid\" : \"dnet:subject_classification_typologies\", \"@schemename\" : \"dnet:subject_classification_typologies\", \"@inferred\" : true, \"@inferenceprovenance\" : \"update\", \"@provenanceaction\" : \"subject:fos\", \"$\" : \"03 medical and health sciences\" } ], \"language\" : { \"@classid\" : \"und\", \"@classname\" : \"Undetermined\", \"@schemeid\" : \"dnet:languages\", \"@schemename\" : \"dnet:languages\" }, \"relevantdate\" : [ { \"@classid\" : \"created\", \"@classname\" : \"created\", \"@schemeid\" : \"dnet:dataCite_date\", \"@schemename\" : \"dnet:dataCite_date\", \"$\" : \"2022-11-25\" }, { \"@classid\" : \"published-print\", \"@classname\" : \"published-print\", \"@schemeid\" : \"dnet:dataCite_date\", \"@schemename\" : \"dnet:dataCite_date\", \"$\" : \"2020-02-01\" } ], \"publisher\" : { \"$\" : \"CABI Publishing\" }, \"source\" : { \"$\" : \"Crossref\" }, \"resulttype\" : { \"@classid\" : \"dataset\", \"@classname\" : \"dataset\", \"@schemeid\" : \"dnet:result_typologies\", \"@schemename\" : \"dnet:result_typologies\" }, \"resourcetype\" : { \"@classid\" : \"dataset\", \"@classname\" : \"dataset\", \"@schemeid\" : \"dnet:result_typologies\", \"@schemename\" : \"dnet:result_typologies\" }, \"datainfo\" : { \"inferred\" : { \"$\" : false }, \"deletedbyinference\" : { \"$\" : false }, \"trust\" : { \"$\" : \"0.91\" }, \"inferenceprovenance\" : { \"$\" : \"null\" }, \"provenanceaction\" : { \"@classid\" : \"sysimport:actionset\", \"@classname\" : \"Harvested\", \"@schemeid\" : \"dnet:provenanceActions\", \"@schemename\" : \"dnet:provenanceActions\" } }, \"rels\" : null, \"children\" : { \"instance\" : { \"accessright\" : { \"@classid\" : \"UNKNOWN\", \"@classname\" : \"unspecified\", \"@schemeid\" : \"dnet:access_modes\", \"@schemename\" : \"dnet:access_modes\" }, \"collectedfrom\" : { \"@name\" : \"Crossref\", \"@id\" : \"openaire____::081b82f96300b6a6e3d282bad31cb6e2\" }, \"hostedby\" : { \"@name\" : \"Unknown Repository\", \"@id\" : \"openaire____::55045bd2a65019fd8e6741a755395c8c\" }, \"dateofacceptance\" : { \"$\" : \"2020-02-01\" }, \"instancetype\" : { \"@classid\" : \"0021\", \"@classname\" : \"Dataset\", \"@schemeid\" : \"dnet:publication_resource\", \"@schemename\" : \"dnet:publication_resource\" }, \"pid\" : { \"@classid\" : \"doi\", \"@classname\" : \"Digital Object Identifier\", \"@schemeid\" : \"dnet:pid_types\", \"@schemename\" : \"dnet:pid_types\", \"$\" : \"10.1079/pwkb.20167801211\" }, \"refereed\" : { \"@classid\" : \"0002\", \"@classname\" : \"nonPeerReviewed\", \"@schemeid\" : \"dnet:review_levels\", \"@schemename\" : \"dnet:review_levels\" }, \"webresource\" : { \"url\" : { \"$\" : \"https://doi.org/10.1079/pwkb.20167801211\" } } } } } } } }, { \"header\" : { \"dri:objIdentifier\" : { \"$\" : \"doi_________::fb46fa21374df0f5e903ddb25b8e2e27\" }, \"dri:dateOfCollection\" : { \"$\" : \"2026-06-23T10:03:18.989172201\" }, \"dri:dateOfTransformation\" : null }, \"metadata\" : { \"oaf:entity\" : { \"@xsi:schemaLocation\" : \"http://namespace.openaire.eu/oaf https://www.openaire.eu/schema/1.0/oaf-1.0.xsd\", \"oaf:result\" : { \"collectedfrom\" : { \"@name\" : \"Crossref\", \"@id\" : \"openaire____::081b82f96300b6a6e3d282bad31cb6e2\" }, \"originalId\" : [ { \"$\" : \"10.1079/pwkb.20157800762\" }, { \"$\" : \"50|doiboost____|fb46fa21374df0f5e903ddb25b8e2e27\" } ], \"pid\" : { \"@classid\" : \"doi\", \"@classname\" : \"Digital Object Identifier\", \"@schemeid\" : \"dnet:pid_types\", \"@schemename\" : \"dnet:pid_types\", \"$\" : \"10.1079/pwkb.20157800762\" }, \"measure\" : [ { \"@id\" : \"influence\", \"@score\" : \"2.2251732E-9\", \"@class\" : \"C5\" }, { \"@id\" : \"popularity\", \"@score\" : \"1.1551581E-9\", \"@class\" : \"C5\" }, { \"@id\" : \"influence_alt\", \"@score\" : \"0\", \"@class\" : \"C5\" }, { \"@id\" : \"citationCount\", \"@score\" : \"0\", \"@class\" : \"C5\" }, { \"@id\" : \"popularity_alt\", \"@score\" : \"0.0\", \"@class\" : \"C5\" }, { \"@id\" : \"impulse\", \"@score\" : \"0\", \"@class\" : \"C5\" } ], \"title\" : [ { \"@classid\" : \"main title\", \"@classname\" : \"main title\", \"@schemeid\" : \"dnet:dataCite_title\", \"@schemename\" : \"dnet:dataCite_title\", \"$\" : \"Yellow rust on wheat (Stripe rust)-Ethiopia\" }, { \"@classid\" : \"subtitle\", \"@classname\" : \"subtitle\", \"@schemeid\" : \"dnet:dataCite_title\", \"@schemename\" : \"dnet:dataCite_title\", \"$\" : \"<i>Puccinia Striiformis</i>             ; Yesinde  wag\" } ], \"bestaccessright\" : { \"@classid\" : \"UNKNOWN\", \"@classname\" : \"unspecified\", \"@schemeid\" : \"dnet:access_modes\", \"@schemename\" : \"dnet:access_modes\" }, \"creator\" : [ { \"@rank\" : \"1\", \"@name\" : \"F.\", \"@surname\" : \"Sileshi\", \"$\" : \"F. Sileshi\" }, { \"@rank\" : \"2\", \"@name\" : \"T.\", \"@surname\" : \"Ero\", \"$\" : \"T. Ero\" }, { \"@rank\" : \"3\", \"@name\" : \"A.\", \"@surname\" : \"Seid\", \"$\" : \"A. Seid\" }, { \"@rank\" : \"4\", \"@name\" : \"D.\", \"@surname\" : \"Hirpa\", \"$\" : \"D. Hirpa\" } ], \"dateofacceptance\" : { \"$\" : \"2020-02-01\" }, \"subject\" : [ { \"@classid\" : \"FOS\", \"@classname\" : \"Fields of Science and Technology classification\", \"@schemeid\" : \"dnet:subject_classification_typologies\", \"@schemename\" : \"dnet:subject_classification_typologies\", \"@inferred\" : true, \"@inferenceprovenance\" : \"update\", \"@provenanceaction\" : \"subject:fos\", \"$\" : \"0301 basic medicine\" }, { \"@classid\" : \"FOS\", \"@classname\" : \"Fields of Science and Technology classification\", \"@schemeid\" : \"dnet:subject_classification_typologies\", \"@schemename\" : \"dnet:subject_classification_typologies\", \"@inferred\" : true, \"@inferenceprovenance\" : \"update\", \"@provenanceaction\" : \"subject:fos\", \"$\" : \"03 medical and health sciences\" } ], \"language\" : { \"@classid\" : \"und\", \"@classname\" : \"Undetermined\", \"@schemeid\" : \"dnet:languages\", \"@schemename\" : \"dnet:languages\" }, \"relevantdate\" : [ { \"@classid\" : \"created\", \"@classname\" : \"created\", \"@schemeid\" : \"dnet:dataCite_date\", \"@schemename\" : \"dnet:dataCite_date\", \"$\" : \"2022-11-24\" }, { \"@classid\" : \"published-print\", \"@classname\" : \"published-print\", \"@schemeid\" : \"dnet:dataCite_date\", \"@schemename\" : \"dnet:dataCite_date\", \"$\" : \"2020-02-01\" } ], \"publisher\" : { \"$\" : \"CABI Publishing\" }, \"source\" : { \"$\" : \"Crossref\" }, \"resulttype\" : { \"@classid\" : \"dataset\", \"@classname\" : \"dataset\", \"@schemeid\" : \"dnet:result_typologies\", \"@schemename\" : \"dnet:result_typologies\" }, \"resourcetype\" : { \"@classid\" : \"dataset\", \"@classname\" : \"dataset\", \"@schemeid\" : \"dnet:result_typologies\", \"@schemename\" : \"dnet:result_typologies\" }, \"datainfo\" : { \"inferred\" : { \"$\" : false }, \"deletedbyinference\" : { \"$\" : false }, \"trust\" : { \"$\" : \"0.91\" }, \"inferenceprovenance\" : { \"$\" : \"null\" }, \"provenanceaction\" : { \"@classid\" : \"sysimport:actionset\", \"@classname\" : \"Harvested\", \"@schemeid\" : \"dnet:provenanceActions\", \"@schemename\" : \"dnet:provenanceActions\" } }, \"rels\" : { \"rel\" : { \"@inferred\" : true, \"@trust\" : \"1.0\", \"@inferenceprovenance\" : \"openaire:affiliation:crossref\", \"@provenanceaction\" : \"result:organization:openaireinference\", \"to\" : { \"@class\" : \"hasAuthorInstitution\", \"@scheme\" : \"dnet:result_organization_relations\", \"@type\" : \"organization\", \"$\" : \"openorgs____::8027b62f38c0da85abdeeb24c1e34983\" }, \"legalshortname\" : { \"$\" : \"Ambo University\" }, \"country\" : { \"@classid\" : \"ET\", \"@classname\" : \"Ethiopia\", \"@schemeid\" : \"dnet:countries\", \"@schemename\" : \"dnet:countries\" }, \"websiteurl\" : { \"$\" : \"http://www.ambou.edu.et/\" }, \"legalname\" : { \"$\" : \"Ambo University\" } } }, \"children\" : { \"instance\" : { \"accessright\" : { \"@classid\" : \"UNKNOWN\", \"@classname\" : \"unspecified\", \"@schemeid\" : \"dnet:access_modes\", \"@schemename\" : \"dnet:access_modes\" }, \"collectedfrom\" : { \"@name\" : \"Crossref\", \"@id\" : \"openaire____::081b82f96300b6a6e3d282bad31cb6e2\" }, \"hostedby\" : { \"@name\" : \"Unknown Repository\", \"@id\" : \"openaire____::55045bd2a65019fd8e6741a755395c8c\" }, \"dateofacceptance\" : { \"$\" : \"2020-02-01\" }, \"instancetype\" : { \"@classid\" : \"0021\", \"@classname\" : \"Dataset\", \"@schemeid\" : \"dnet:publication_resource\", \"@schemename\" : \"dnet:publication_resource\" }, \"pid\" : { \"@classid\" : \"doi\", \"@classname\" : \"Digital Object Identifier\", \"@schemeid\" : \"dnet:pid_types\", \"@schemename\" : \"dnet:pid_types\", \"$\" : \"10.1079/pwkb.20157800762\" }, \"refereed\" : { \"@classid\" : \"0002\", \"@classname\" : \"nonPeerReviewed\", \"@schemeid\" : \"dnet:review_levels\", \"@schemename\" : \"dnet:review_levels\" }, \"webresource\" : { \"url\" : { \"$\" : \"https://doi.org/10.1079/pwkb.20157800762\" } } } } } } } }, { \"header\" : { \"dri:objIdentifier\" : { \"$\" : \"doi_dedup___::add41fc792c5886951c3b5f33a1dda4a\" }, \"dri:dateOfCollection\" : { \"$\" : \"2026-06-23T10:03:51.487335662\" }, \"dri:dateOfTransformation\" : null }, \"metadata\" : { \"oaf:entity\" : { \"@xsi:schemaLocation\" : \"http://namespace.openaire.eu/oaf https://www.openaire.eu/schema/1.0/oaf-1.0.xsd\", \"oaf:result\" : { \"collectedfrom\" : [ { \"@name\" : \"Datacite\", \"@id\" : \"openaire____::9e3be59865b2c1c335d32dae2fe7b254\" }, { \"@name\" : \"ZENODO\", \"@id\" : \"opendoar____::358aee4cc897452c00244351e4d91f69\" } ], \"originalId\" : [ { \"$\" : \"50|datacite____::6ee078942ad247d6b2bd261fc487cf21\" }, { \"$\" : \"10.5281/zenodo.10358798\" }, { \"$\" : \"oai:zenodo.org:10358798\" }, { \"$\" : \"50|od______2659::6ee078942ad247d6b2bd261fc487cf21\" }, { \"$\" : \"50|datacite____::add41fc792c5886951c3b5f33a1dda4a\" }, { \"$\" : \"10.5281/zenodo.10358797\" } ], \"pid\" : [ { \"@classid\" : \"doi\", \"@classname\" : \"Digital Object Identifier\", \"@schemeid\" : \"dnet:pid_types\", \"@schemename\" : \"dnet:pid_types\", \"@inferred\" : false, \"@provenanceaction\" : \"sysimport:actionset\", \"@trust\" : \"0.9\", \"$\" : \"10.5281/zenodo.10358798\" }, { \"@classid\" : \"doi\", \"@classname\" : \"Digital Object Identifier\", \"@schemeid\" : \"dnet:pid_types\", \"@schemename\" : \"dnet:pid_types\", \"@inferred\" : false, \"@provenanceaction\" : \"sysimport:actionset\", \"@trust\" : \"0.9\", \"$\" : \"10.5281/zenodo.10358797\" } ], \"measure\" : [ { \"@id\" : \"influence\", \"@score\" : \"2.2251732E-9\", \"@class\" : \"C5\" }, { \"@id\" : \"popularity\", \"@score\" : \"1.323256E-9\", \"@class\" : \"C5\" }, { \"@id\" : \"influence_alt\", \"@score\" : \"0\", \"@class\" : \"C5\" }, { \"@id\" : \"citationCount\", \"@score\" : \"0\", \"@class\" : \"C5\" }, { \"@id\" : \"popularity_alt\", \"@score\" : \"0.0\", \"@class\" : \"C5\" }, { \"@id\" : \"impulse\", \"@score\" : \"0\", \"@class\" : \"C5\" } ], \"title\" : { \"@classid\" : \"main title\", \"@classname\" : \"main title\", \"@schemeid\" : \"dnet:dataCite_title\", \"@schemename\" : \"dnet:dataCite_title\", \"$\" : \"Rusted Pliers\" }, \"bestaccessright\" : { \"@classid\" : \"OPEN\", \"@classname\" : \"Open Access\", \"@schemeid\" : \"dnet:access_modes\", \"@schemename\" : \"dnet:access_modes\" }, \"creator\" : { \"@rank\" : \"1\", \"@surname\" : \"tadeus\", \"$\" : \"tadeus\" }, \"dateofacceptance\" : { \"$\" : \"2021-03-12\" }, \"description\" : { \"$\" : \"Turned out okay for the time it took, and I actually used Normal and Roughness maps.   Free to use! Critique is welcome.  Source: Objaverse 1.0 / Sketchfab\" }, \"subject\" : [ { \"@classid\" : \"FOS\", \"@classname\" : \"Fields of Science and Technology classification\", \"@schemeid\" : \"dnet:subject_classification_typologies\", \"@schemename\" : \"dnet:subject_classification_typologies\", \"@inferred\" : true, \"@inferenceprovenance\" : \"update\", \"@provenanceaction\" : \"subject:fos\", \"$\" : \"0205 materials engineering\" }, { \"@classid\" : \"FOS\", \"@classname\" : \"Fields of Science and Technology classification\", \"@schemeid\" : \"dnet:subject_classification_typologies\", \"@schemename\" : \"dnet:subject_classification_typologies\", \"@inferred\" : true, \"@inferenceprovenance\" : \"update\", \"@provenanceaction\" : \"subject:fos\", \"$\" : \"02 engineering and technology\" } ], \"language\" : { \"@classid\" : \"und\", \"@classname\" : \"Undetermined\", \"@schemeid\" : \"dnet:languages\", \"@schemename\" : \"dnet:languages\" }, \"relevantdate\" : [ { \"@classid\" : \"issued\", \"@classname\" : \"issued\", \"@schemeid\" : \"dnet:dataCite_date\", \"@schemename\" : \"dnet:dataCite_date\", \"$\" : \"2021-03-12\" }, { \"@classid\" : \"updated\", \"@classname\" : \"updated\", \"@schemeid\" : \"dnet:dataCite_date\", \"@schemename\" : \"dnet:dataCite_date\", \"@inferred\" : false, \"@provenanceaction\" : \"sysimport:crosswalk:repository\", \"@trust\" : \"0.9\", \"$\" : \"2026-05-28\" } ], \"publisher\" : { \"$\" : \"Zenodo\" }, \"resulttype\" : { \"@classid\" : \"dataset\", \"@classname\" : \"dataset\", \"@schemeid\" : \"dnet:result_typologies\", \"@schemename\" : \"dnet:result_typologies\" }, \"resourcetype\" : { \"@classid\" : \"UNKNOWN\", \"@classname\" : \"UNKNOWN\", \"@schemeid\" : \"dnet:dataCite_resource\", \"@schemename\" : \"dnet:dataCite_resource\" }, \"lastmetadataupdate\" : { \"$\" : \"2026-05-28\" }, \"storagedate\" : { \"$\" : \"2021-03-12\" }, \"context\" : { \"@id\" : \"eosc\", \"@label\" : \"EOSC\", \"@type\" : \"ri\" }, \"datainfo\" : { \"inferred\" : { \"$\" : true }, \"deletedbyinference\" : { \"$\" : false }, \"trust\" : { \"$\" : \"0.8\" }, \"inferenceprovenance\" : { \"$\" : \"dedup-result-decisiontree-v4\" }, \"provenanceaction\" : { \"@classid\" : \"sysimport:dedup\", \"@classname\" : \"Inferred by OpenAIRE\", \"@schemeid\" : \"dnet:provenanceActions\", \"@schemename\" : \"dnet:provenanceActions\" } }, \"rels\" : null, \"children\" : { \"result\" : [ { \"@objidentifier\" : \"doi_________::add41fc792c5886951c3b5f33a1dda4a\", \"creator\" : { \"$\" : \"tadeus\" }, \"publisher\" : { \"$\" : \"Zenodo\" }, \"description\" : { \"$\" : \"Turned out okay for the time it took, and I actually used Normal and Roughness maps.   Free to use! Critique is welcome.  Source: Objaverse 1.0 / Sketchfab\" }, \"dateofacceptance\" : { \"$\" : \"2021-03-12\" }, \"resulttype\" : { \"@classid\" : \"dataset\", \"@classname\" : \"dataset\", \"@schemeid\" : \"dnet:result_typologies\", \"@schemename\" : \"dnet:result_typologies\" }, \"pid\" : { \"@classid\" : \"doi\", \"@classname\" : \"Digital Object Identifier\", \"@schemeid\" : \"dnet:pid_types\", \"@schemename\" : \"dnet:pid_types\", \"@inferred\" : false, \"@provenanceaction\" : \"sysimport:actionset\", \"@trust\" : \"0.9\", \"$\" : \"10.5281/zenodo.10358797\" }, \"title\" : { \"@classid\" : \"main title\", \"@classname\" : \"main title\", \"@schemeid\" : \"dnet:dataCite_title\", \"@schemename\" : \"dnet:dataCite_title\", \"$\" : \"Rusted Pliers\" }, \"instance\" : { \"accessright\" : { \"@classid\" : \"UNKNOWN\", \"@classname\" : \"unspecified\", \"@schemeid\" : \"dnet:access_modes\", \"@schemename\" : \"dnet:access_modes\" }, \"hostedby\" : { \"@name\" : \"ZENODO\", \"@id\" : \"opendoar____::358aee4cc897452c00244351e4d91f69\" }, \"dateofacceptance\" : { \"$\" : \"2021-03-12\" }, \"instancetype\" : { \"@classid\" : \"0021\", \"@classname\" : \"Dataset\", \"@schemeid\" : \"dnet:publication_resource\", \"@schemename\" : \"dnet:publication_resource\" }, \"refereed\" : { \"@classid\" : \"0002\", \"@classname\" : \"nonPeerReviewed\", \"@schemeid\" : \"dnet:review_levels\", \"@schemename\" : \"dnet:review_levels\" }, \"license\" : { \"$\" : \"CC BY\" }, \"url\" : { \"$\" : \"https://dx.doi.org/10.5281/zenodo.10358797\" }, \"webresource\" : { \"url\" : { \"$\" : \"https://dx.doi.org/10.5281/zenodo.10358797\" } } }, \"collectedfrom\" : { \"@name\" : \"Datacite\", \"@id\" : \"openaire____::9e3be59865b2c1c335d32dae2fe7b254\" } }, { \"@objidentifier\" : \"doi_________::6ee078942ad247d6b2bd261fc487cf21\", \"creator\" : { \"$\" : \"tadeus\" }, \"publisher\" : { \"$\" : \"Zenodo\" }, \"description\" : { \"$\" : \"Turned out okay for the time it took, and I actually used Normal and Roughness maps.   Free to use! Critique is welcome.  Source: Objaverse 1.0 / Sketchfab\" }, \"instance\" : [ { \"accessright\" : { \"@classid\" : \"OPEN\", \"@classname\" : \"Open Access\", \"@schemeid\" : \"dnet:access_modes\", \"@schemename\" : \"dnet:access_modes\" }, \"hostedby\" : { \"@name\" : \"ZENODO\", \"@id\" : \"opendoar____::358aee4cc897452c00244351e4d91f69\" }, \"dateofacceptance\" : { \"$\" : \"2021-03-12\" }, \"instancetype\" : { \"@classid\" : \"0021\", \"@classname\" : \"Dataset\", \"@schemeid\" : \"dnet:publication_resource\", \"@schemename\" : \"dnet:publication_resource\" }, \"refereed\" : { \"@classid\" : \"0002\", \"@classname\" : \"nonPeerReviewed\", \"@schemeid\" : \"dnet:review_levels\", \"@schemename\" : \"dnet:review_levels\" }, \"license\" : { \"$\" : \"CC BY\" }, \"url\" : [ { \"$\" : \"http://dx.doi.org/10.5281/zenodo.10358798\" }, { \"$\" : \"https://zenodo.org/records/10358798\" } ], \"webresource\" : [ { \"url\" : { \"$\" : \"http://dx.doi.org/10.5281/zenodo.10358798\" } }, { \"url\" : { \"$\" : \"https://zenodo.org/records/10358798\" } } ] }, { \"accessright\" : { \"@classid\" : \"UNKNOWN\", \"@classname\" : \"unspecified\", \"@schemeid\" : \"dnet:access_modes\", \"@schemename\" : \"dnet:access_modes\" }, \"hostedby\" : { \"@name\" : \"ZENODO\", \"@id\" : \"opendoar____::358aee4cc897452c00244351e4d91f69\" }, \"dateofacceptance\" : { \"$\" : \"2021-03-12\" }, \"instancetype\" : { \"@classid\" : \"0021\", \"@classname\" : \"Dataset\", \"@schemeid\" : \"dnet:publication_resource\", \"@schemename\" : \"dnet:publication_resource\" }, \"refereed\" : { \"@classid\" : \"0002\", \"@classname\" : \"nonPeerReviewed\", \"@schemeid\" : \"dnet:review_levels\", \"@schemename\" : \"dnet:review_levels\" }, \"license\" : { \"$\" : \"CC BY\" }, \"url\" : { \"$\" : \"https://dx.doi.org/10.5281/zenodo.10358798\" }, \"webresource\" : { \"url\" : { \"$\" : \"https://dx.doi.org/10.5281/zenodo.10358798\" } } } ], \"dateofacceptance\" : { \"$\" : \"2021-03-12\" }, \"resulttype\" : { \"@classid\" : \"dataset\", \"@classname\" : \"dataset\", \"@schemeid\" : \"dnet:result_typologies\", \"@schemename\" : \"dnet:result_typologies\" }, \"title\" : { \"@classid\" : \"main title\", \"@classname\" : \"main title\", \"@schemeid\" : \"dnet:dataCite_title\", \"@schemename\" : \"dnet:dataCite_title\", \"$\" : \"Rusted Pliers\" }, \"collectedfrom\" : [ { \"@name\" : \"ZENODO\", \"@id\" : \"opendoar____::358aee4cc897452c00244351e4d91f69\" }, { \"@name\" : \"Datacite\", \"@id\" : \"openaire____::9e3be59865b2c1c335d32dae2fe7b254\" } ], \"pid\" : { \"@classid\" : \"doi\", \"@classname\" : \"Digital Object Identifier\", \"@schemeid\" : \"dnet:pid_types\", \"@schemename\" : \"dnet:pid_types\", \"@inferred\" : false, \"@provenanceaction\" : \"sysimport:actionset\", \"@trust\" : \"0.9\", \"$\" : \"10.5281/zenodo.10358798\" } } ], \"instance\" : [ { \"accessright\" : { \"@classid\" : \"UNKNOWN\", \"@classname\" : \"unspecified\", \"@schemeid\" : \"dnet:access_modes\", \"@schemename\" : \"dnet:access_modes\" }, \"collectedfrom\" : { \"@name\" : \"Datacite\", \"@id\" : \"openaire____::9e3be59865b2c1c335d32dae2fe7b254\" }, \"hostedby\" : { \"@name\" : \"ZENODO\", \"@id\" : \"opendoar____::358aee4cc897452c00244351e4d91f69\" }, \"dateofacceptance\" : { \"$\" : \"2021-03-12\" }, \"instancetype\" : { \"@classid\" : \"0021\", \"@classname\" : \"Dataset\", \"@schemeid\" : \"dnet:publication_resource\", \"@schemename\" : \"dnet:publication_resource\" }, \"pid\" : { \"@classid\" : \"doi\", \"@classname\" : \"Digital Object Identifier\", \"@schemeid\" : \"dnet:pid_types\", \"@schemename\" : \"dnet:pid_types\", \"@inferred\" : false, \"@provenanceaction\" : \"sysimport:actionset\", \"@trust\" : \"0.9\", \"$\" : \"10.5281/zenodo.10358797\" }, \"refereed\" : { \"@classid\" : \"0002\", \"@classname\" : \"nonPeerReviewed\", \"@schemeid\" : \"dnet:review_levels\", \"@schemename\" : \"dnet:review_levels\" }, \"license\" : { \"$\" : \"CC BY\" }, \"webresource\" : { \"url\" : { \"$\" : \"https://doi.org/10.5281/zenodo.10358797\" } } }, { \"accessright\" : { \"@classid\" : \"OPEN\", \"@classname\" : \"Open Access\", \"@schemeid\" : \"dnet:access_modes\", \"@schemename\" : \"dnet:access_modes\" }, \"collectedfrom\" : [ { \"@name\" : \"Datacite\", \"@id\" : \"openaire____::9e3be59865b2c1c335d32dae2fe7b254\" }, { \"@name\" : \"ZENODO\", \"@id\" : \"opendoar____::358aee4cc897452c00244351e4d91f69\" } ], \"hostedby\" : [ { \"@name\" : \"ZENODO\", \"@id\" : \"opendoar____::358aee4cc897452c00244351e4d91f69\" }, { \"@name\" : \"ZENODO\", \"@id\" : \"opendoar____::358aee4cc897452c00244351e4d91f69\" } ], \"dateofacceptance\" : { \"$\" : \"2021-03-12\" }, \"instancetype\" : { \"@classid\" : \"0021\", \"@classname\" : \"Dataset\", \"@schemeid\" : \"dnet:publication_resource\", \"@schemename\" : \"dnet:publication_resource\" }, \"pid\" : [ { \"@classid\" : \"doi\", \"@classname\" : \"Digital Object Identifier\", \"@schemeid\" : \"dnet:pid_types\", \"@schemename\" : \"dnet:pid_types\", \"@inferred\" : false, \"@provenanceaction\" : \"sysimport:crosswalk:repository\", \"@trust\" : \"0.9\", \"$\" : \"10.5281/zenodo.10358798\" }, { \"@classid\" : \"doi\", \"@classname\" : \"Digital Object Identifier\", \"@schemeid\" : \"dnet:pid_types\", \"@schemename\" : \"dnet:pid_types\", \"@inferred\" : false, \"@provenanceaction\" : \"sysimport:actionset\", \"@trust\" : \"0.9\", \"$\" : \"10.5281/zenodo.10358798\" } ], \"alternateidentifier\" : { \"@classid\" : \"oai\", \"@classname\" : \"Open Archives Initiative\", \"@schemeid\" : \"dnet:pid_types\", \"@schemename\" : \"dnet:pid_types\", \"$\" : \"oai:zenodo.org:10358798\" }, \"refereed\" : { \"@classid\" : \"0002\", \"@classname\" : \"nonPeerReviewed\", \"@schemeid\" : \"dnet:review_levels\", \"@schemename\" : \"dnet:review_levels\" }, \"license\" : { \"$\" : \"CC BY\" }, \"webresource\" : { \"url\" : { \"$\" : \"https://doi.org/10.5281/zenodo.10358798\" } } } ] } } } } }, { \"header\" : { \"dri:objIdentifier\" : { \"$\" : \"_____OmicsDI::005bd1ba83f6891272751e02e857be3a\" }, \"dri:dateOfCollection\" : { \"$\" : \"2026-06-23T10:02:59.038734293\" }, \"dri:dateOfTransformation\" : { \"$\" : \"2022-04-14T14:00:38.728Z\" } }, \"metadata\" : { \"oaf:entity\" : { \"@xsi:schemaLocation\" : \"http://namespace.openaire.eu/oaf https://www.openaire.eu/schema/1.0/oaf-1.0.xsd\", \"oaf:result\" : { \"collectedfrom\" : { \"@name\" : \"Omics Discovery Index (OmicsDI)\", \"@id\" : \"rest________::f63e28997bb5aee636a4d21ab2a0a5f9\" }, \"originalId\" : [ { \"$\" : \"PRJNA347281\" }, { \"$\" : \"50|_____OmicsDI::005bd1ba83f6891272751e02e857be3a\" } ], \"measure\" : [ { \"@id\" : \"influence\", \"@score\" : \"2.2251732E-9\", \"@class\" : \"C5\" }, { \"@id\" : \"popularity\", \"@score\" : \"1.8635508E-10\", \"@class\" : \"C5\" }, { \"@id\" : \"influence_alt\", \"@score\" : \"0\", \"@class\" : \"C5\" }, { \"@id\" : \"citationCount\", \"@score\" : \"0\", \"@class\" : \"C5\" }, { \"@id\" : \"popularity_alt\", \"@score\" : \"0.0\", \"@class\" : \"C5\" }, { \"@id\" : \"impulse\", \"@score\" : \"0\", \"@class\" : \"C5\" } ], \"title\" : { \"@classid\" : \"main title\", \"@classname\" : \"main title\", \"@schemeid\" : \"dnet:dataCite_title\", \"@schemename\" : \"dnet:dataCite_title\", \"@inferred\" : false, \"@provenanceaction\" : \"sysimport:crosswalk:datasetarchive\", \"@trust\" : \"0.9\", \"$\" : \"METAL RUST\" }, \"bestaccessright\" : { \"@classid\" : \"UNKNOWN\", \"@classname\" : \"unspecified\", \"@schemeid\" : \"dnet:access_modes\", \"@schemename\" : \"dnet:access_modes\" }, \"description\" : { \"$\" : \"METAL RUST Metagenome\" }, \"subject\" : [ { \"@classid\" : \"FOS\", \"@classname\" : \"Fields of Science and Technology classification\", \"@schemeid\" : \"dnet:subject_classification_typologies\", \"@schemename\" : \"dnet:subject_classification_typologies\", \"@inferred\" : true, \"@inferenceprovenance\" : \"update\", \"@provenanceaction\" : \"subject:fos\", \"$\" : \"0206 medical engineering\" }, { \"@classid\" : \"FOS\", \"@classname\" : \"Fields of Science and Technology classification\", \"@schemeid\" : \"dnet:subject_classification_typologies\", \"@schemename\" : \"dnet:subject_classification_typologies\", \"@inferred\" : true, \"@inferenceprovenance\" : \"update\", \"@provenanceaction\" : \"subject:fos\", \"$\" : \"02 engineering and technology\" }, { \"@classid\" : \"keyword\", \"@classname\" : \"keyword\", \"@schemeid\" : \"dnet:subject_classification_typologies\", \"@schemename\" : \"dnet:subject_classification_typologies\", \"@inferred\" : false, \"@provenanceaction\" : \"sysimport:crosswalk:datasetarchive\", \"@trust\" : \"0.9\", \"$\" : \"Genomics\" } ], \"language\" : { \"@classid\" : \"und\", \"@classname\" : \"Undetermined\", \"@schemeid\" : \"dnet:languages\", \"@schemename\" : \"dnet:languages\" }, \"resulttype\" : { \"@classid\" : \"dataset\", \"@classname\" : \"dataset\", \"@schemeid\" : \"dnet:result_typologies\", \"@schemename\" : \"dnet:result_typologies\" }, \"resourcetype\" : { \"@classid\" : \"UNKNOWN\", \"@classname\" : \"UNKNOWN\", \"@schemeid\" : \"dnet:dataCite_resource\", \"@schemename\" : \"dnet:dataCite_resource\" }, \"datainfo\" : { \"inferred\" : { \"$\" : false }, \"deletedbyinference\" : { \"$\" : false }, \"trust\" : { \"$\" : \"0.9\" }, \"inferenceprovenance\" : null, \"provenanceaction\" : { \"@classid\" : \"sysimport:crosswalk:datasetarchive\", \"@classname\" : \"Harvested\", \"@schemeid\" : \"dnet:provenanceActions\", \"@schemename\" : \"dnet:provenanceActions\" } }, \"rels\" : null, \"children\" : { \"instance\" : { \"accessright\" : { \"@classid\" : \"UNKNOWN\", \"@classname\" : \"unspecified\", \"@schemeid\" : \"dnet:access_modes\", \"@schemename\" : \"dnet:access_modes\" }, \"collectedfrom\" : { \"@name\" : \"Omics Discovery Index (OmicsDI)\", \"@id\" : \"rest________::f63e28997bb5aee636a4d21ab2a0a5f9\" }, \"hostedby\" : { \"@name\" : \"European Nucleotide Archive\", \"@id\" : \"fairsharing_::8c3039bd5842dca3d944faab91447818\" }, \"instancetype\" : { \"@classid\" : \"0021\", \"@classname\" : \"Dataset\", \"@schemeid\" : \"dnet:publication_resource\", \"@schemename\" : \"dnet:publication_resource\" }, \"refereed\" : { \"@classid\" : \"0002\", \"@classname\" : \"nonPeerReviewed\", \"@schemeid\" : \"dnet:review_levels\", \"@schemename\" : \"dnet:review_levels\" }, \"webresource\" : { \"url\" : { \"$\" : \"https://www.omicsdi.org/dataset/omics_ena_project/PRJNA347281\" } } } } } } } } ] }, \"browseResults\" : null } }"
  },
  "golden_results": {
    "results": [
      {
        "Main": {
          "url": "https://doi.org/10.5446/s_1065",
          "normalized_url": "https://doi.org/10.5446/s_1065",
          "title": "Rust Belt Rust 2016",
          "content": "",
          "engine": "openairedatasets",
          "engines": [],
          "score": 0.0,
          "positions": [],
          "priority": "",
          "template": "Default"
        }
      },
      {
        "Main": {
          "url": "https://doi.org/10.24894/sprengglossarium_r05031",
          "normalized_url": "https://doi.org/10.24894/sprengglossarium_r05031",
          "title": "rust",
          "content": "",
          "engine": "openairedatasets",
          "engines": [],
          "score": 0.0,
          "positions": [],
          "priority": "",
          "template": "Default"
        }
      },
      {
        "Main": {
          "url": "https://doi.org/10.5446/s_1055",
          "normalized_url": "https://doi.org/10.5446/s_1055",
          "title": "Rust Belt Rust Conference 2019",
          "content": "",
          "engine": "openairedatasets",
          "engines": [],
          "score": 0.0,
          "positions": [],
          "priority": "",
          "template": "Default"
        }
      },
      {
        "Main": {
          "url": "https://doi.org/10.24894/sprengglossarium_r05025",
          "normalized_url": "https://doi.org/10.24894/sprengglossarium_r05025",
          "title": "Rust",
          "content": "",
          "engine": "openairedatasets",
          "engines": [],
          "score": 0.0,
          "positions": [],
          "priority": "",
          "template": "Default"
        }
      },
      {
        "Main": {
          "url": "https://doi.org/10.24894/sprengglossarium_r05023",
          "normalized_url": "https://doi.org/10.24894/sprengglossarium_r05023",
          "title": "rust",
          "content": "",
          "engine": "openairedatasets",
          "engines": [],
          "score": 0.0,
          "positions": [],
          "priority": "",
          "template": "Default"
        }
      },
      {
        "Main": {
          "url": "https://doi.org/10.1163/2405-8262_rgg4_sim_025121",
          "normalized_url": "https://doi.org/10.1163/2405-8262_rgg4_sim_025121",
          "title": "Rust",
          "content": "",
          "engine": "openairedatasets",
          "engines": [],
          "score": 0.0,
          "positions": [],
          "priority": "",
          "template": "Default"
        }
      },
      {
        "Main": {
          "url": "https://doi.org/10.1079/pwkb.20167801211",
          "normalized_url": "https://doi.org/10.1079/pwkb.20167801211",
          "title": "Stem rust (black rust) on wheat-Ethiopia",
          "content": "",
          "engine": "openairedatasets",
          "engines": [],
          "score": 0.0,
          "positions": [],
          "priority": "",
          "template": "Default"
        }
      },
      {
        "Main": {
          "url": "https://doi.org/10.1079/pwkb.20157800762",
          "normalized_url": "https://doi.org/10.1079/pwkb.20157800762",
          "title": "Yellow rust on wheat (Stripe rust)-Ethiopia",
          "content": "",
          "engine": "openairedatasets",
          "engines": [],
          "score": 0.0,
          "positions": [],
          "priority": "",
          "template": "Default"
        }
      },
      {
        "Main": {
          "url": "https://doi.org/10.5281/zenodo.10358797",
          "normalized_url": "https://doi.org/10.5281/zenodo.10358797",
          "title": "Rusted Pliers",
          "content": "Turned out okay for the time it took, and I actually used Normal and Roughness maps. Free to use! Critique is welcome. Source: Objaverse 1.0 / Sketchfab",
          "engine": "openairedatasets",
          "engines": [],
          "score": 0.0,
          "positions": [],
          "priority": "",
          "template": "Default"
        }
      },
      {
        "Main": {
          "url": "https://www.omicsdi.org/dataset/omics_ena_project/PRJNA347281",
          "normalized_url": "https://www.omicsdi.org/dataset/omics_ena_project/PRJNA347281",
          "title": "METAL RUST",
          "content": "METAL RUST Metagenome",
          "engine": "openairedatasets",
          "engines": [],
          "score": 0.0,
          "positions": [],
          "priority": "",
          "template": "Default"
        }
      }
    ],
    "answers": [],
    "suggestions": [],
    "corrections": [],
    "infoboxes": []
  }
}